rgwadmin/__init__.py
rgwadmin/exceptions.py
rgwadmin/py.typed
rgwadmin/rgw.py
rgwadmin/user.py
rgwadmin/utils.py
rgwadmin-2.4.5.dist-info/LICENSE
rgwadmin-2.4.5.dist-info/METADATA
rgwadmin-2.4.5.dist-info/WHEEL
rgwadmin-2.4.5.dist-info/top_level.txt
rgwadmin-2.4.5.dist-info/RECORD
