Metadata-Version: 2.1
Name: rgwadmin
Version: 2.4.5
Summary: Python Rados Gateway Admin API
Home-page: https://github.com/UMIACS/rgwadmin
Author: Derek Yarnell
Author-email: derek@umiacs.umd.edu
Maintainer: UMIACS Staff
Maintainer-email: github@umiacs.umd.edu
License: LGPL v2.1
Keywords: ceph,radosgw,admin api
Classifier: Development Status :: 5 - Production/Stable
Classifier: Programming Language :: Python :: 3
Classifier: Programming Language :: Python :: 3.5
Classifier: Programming Language :: Python :: 3.6
License-File: LICENSE
Requires-Dist: requests
Requires-Dist: requests-aws4auth
